{
  // 可以使用 uni-simple-router 来定义类似vue的路由，暂时不研究
  "pages": [
    {
      "path": "pages/index/login"
    },
    {
      "path": "pages/tab/session"
    },
    {
      "path": "pages/index/register"
    },
    // {
    //   "path": "pages/other/session_detail",
    //   "style": {
    //     "app-plus": {
    //       // 软键盘弹出模式，支持 adjustResize、adjustPan 两种模式 主要解决弹出键盘页面错乱问题
    //       "softinputMode": "adjustResize"
    //     }
    //   }
    // },
   
    {
      "path": "pages/tab/a_book"
    },
    {
      "path": "pages/tab/my"
    }
  ],
  "tabBar": {
    "color": "#7A7E83",
    "selectedColor": "#3cc51f",
    "borderStyle": "black",
    "backgroundColor": "#ffffff",
    "list": [
      {
        "pagePath": "pages/tab/session",
        "iconPath": "static/icon/icon-my.png",
        "selectedIconPath": "static/icon/icon-a-my.png",
        "text": "组件"
      },
      {
        "pagePath": "pages/tab/a_book",
        "iconPath": "static/icon/icon-my.png",
        "selectedIconPath": "static/icon/icon-a-my.png",
        "text": "接口"
      },
      {
        "pagePath": "pages/tab/my",
        "iconPath": "static/icon/icon-my.png",
        "selectedIconPath": "static/icon/icon-a-my.png",
        "text": "接口"
      }
    ]
  },

  "globalStyle": {
    "navigationBarTextStyle": "black",
    "navigationBarTitleText": "uni-app",
    "navigationBarBackgroundColor": "#F8F8F8",
    "backgroundColor": "#F8F8F8",
    "app-plus": {
      "titleNView": false
    }
  }
}
